palmari/__init__.py
palmari/_runner.py
palmari/_widget.py
palmari/napari.yaml
palmari/_tests/__init__.py
palmari/_tests/test_widget.py
palmari/data_structure/__init__.py
palmari/data_structure/acquisition.py
palmari/data_structure/experiment.py
palmari/image_tools/__init__.py
palmari/image_tools/cell_mask.py
palmari/image_tools/correct_drift.py
palmari/image_tools/density_filtering.py
palmari/image_tools/intensity.py
palmari/image_tools/localization.py
palmari/processing/__init__.py
palmari/processing/edit_pipeline_window.py
palmari/processing/image_pipeline.py
palmari/processing/image_pipeline_widget.py
palmari/processing/utils.py
palmari/processing/steps/__init__.py
palmari/processing/steps/base.py
palmari/processing/steps/drift_corrector.py
palmari/processing/steps/quot_localizer.py
palmari/processing/steps/quot_tracker.py
palmari/processing/steps/trackpy_tracker.py
palmari/processing/steps/window_percentile.py
palmari/quot/__init__.py
palmari/quot/__main__.py
palmari/quot/chunkFilter.py
palmari/quot/core.py
palmari/quot/findSpots.py
palmari/quot/helper.py
palmari/quot/mask.py
palmari/quot/measureGain.py
palmari/quot/plot.py
palmari/quot/read.py
palmari/quot/subpixel.py
palmari/quot/track.py
palmari/quot/trajUtils.py
palmari-0.3.0.dist-info/AUTHORS.rst
palmari-0.3.0.dist-info/LICENSE
palmari-0.3.0.dist-info/METADATA
palmari-0.3.0.dist-info/WHEEL
palmari-0.3.0.dist-info/entry_points.txt
palmari-0.3.0.dist-info/top_level.txt
palmari-0.3.0.dist-info/RECORD
