Metadata-Version: 2.1
Name: palmari
Version: 0.3.0
Summary: Palmari provides a plugin to analyze PALM movies, as well as microscope recordings of other SMLM-based SPT modalities. Set up your pipeline on one file, run it on a folder !
Home-page: https://github.com/hippover/palmari
Author: Hippolyte Verdier
Author-email: hverdier@pasteur.fr
License: "CeCILL"
Project-URL: Bug Tracker, https://github.com/hippover/palmari/issues
Project-URL: Documentation, https://palmari.readthedocs.io/en/latest/
Project-URL: Source Code, https://github.com/hippover/palmari
Project-URL: User Support, https://github.com/hippover/palmari/issues
Classifier: Development Status :: 4 - Beta
Classifier: Intended Audience :: Science/Research
Classifier: Framework :: napari
Classifier: Environment :: Plugins
Classifier: Programming Language :: Python
Classifier: Programming Language :: Python :: 3
Classifier: Programming Language :: Python :: 3.8
Classifier: Programming Language :: Python :: 3.9
Classifier: Programming Language :: Python :: 3.10
Classifier: Topic :: Scientific/Engineering :: Image Processing
Classifier: Operating System :: OS Independent
Classifier: License :: OSI Approved :: CEA CNRS Inria Logiciel Libre License, version 2.1 (CeCILL-2.1)
Requires-Python: >=3.8
License-File: LICENSE
License-File: AUTHORS.rst
Requires-Dist: click
Requires-Dist: dask (>=2022.1.0)
Requires-Dist: dask-image (>=2021.12.0)
Requires-Dist: imageio-ffmpeg
Requires-Dist: magicgui (>=0.5.0)
Requires-Dist: matplotlib (>=3.5)
Requires-Dist: munkres
Requires-Dist: napari
Requires-Dist: napari-aicsimageio
Requires-Dist: numpy
Requires-Dist: pandas
Requires-Dist: pyyaml
Requires-Dist: qtpy
Requires-Dist: scikit-image (>=0.18.3)
Requires-Dist: scikit-learn
Requires-Dist: toml
Requires-Dist: tqdm
Requires-Dist: trackpy (>=0.5.0)
Provides-Extra: testing
Requires-Dist: tox ; extra == 'testing'
Requires-Dist: PyQt5 ; extra == 'testing'
Requires-Dist: pytest ; extra == 'testing'
Requires-Dist: pytest-cov ; extra == 'testing'
Requires-Dist: pytest-qt ; extra == 'testing'
